{"nodes": [{"id": "d_aegiscore_intelligence_platform_aegiscore_intelligence_platform_frontend_src_lib_api_compliance_ts", "label": "api-compliance.ts", "file_type": "code", "source_file": "D:\\AegisCore Intelligence Platform\\AegisCore Intelligence Platform\\frontend\\src\\lib\\api-compliance.ts", "source_location": "L1"}, {"id": "api_compliance_platformgetsecurityscore", "label": "platformGetSecurityScore()", "file_type": "code", "source_file": "D:\\AegisCore Intelligence Platform\\AegisCore Intelligence Platform\\frontend\\src\\lib\\api-compliance.ts", "source_location": "L42"}, {"id": "api_compliance_platformgetsecurityevents", "label": "platformGetSecurityEvents()", "file_type": "code", "source_file": "D:\\AegisCore Intelligence Platform\\AegisCore Intelligence Platform\\frontend\\src\\lib\\api-compliance.ts", "source_location": "L57"}, {"id": "api_compliance_platformgetcomplianceframeworks", "label": "platformGetComplianceFrameworks()", "file_type": "code", "source_file": "D:\\AegisCore Intelligence Platform\\AegisCore Intelligence Platform\\frontend\\src\\lib\\api-compliance.ts", "source_location": "L75"}, {"id": "api_compliance_platformrecalculatecompliance", "label": "platformRecalculateCompliance()", "file_type": "code", "source_file": "D:\\AegisCore Intelligence Platform\\AegisCore Intelligence Platform\\frontend\\src\\lib\\api-compliance.ts", "source_location": "L90"}], "edges": [{"source": "d_aegiscore_intelligence_platform_aegiscore_intelligence_platform_frontend_src_lib_api_compliance_ts", "target": "d_aegiscore_intelligence_platform_aegiscore_intelligence_platform_frontend_src_lib_api", "relation": "imports_from", "confidence": "EXTRACTED", "source_file": "D:\\AegisCore Intelligence Platform\\AegisCore Intelligence Platform\\frontend\\src\\lib\\api-compliance.ts", "source_location": "L4", "weight": 1.0}, {"source": "d_aegiscore_intelligence_platform_aegiscore_intelligence_platform_frontend_src_lib_api_compliance_ts", "target": "api_compliance_platformgetsecurityscore", "relation": "contains", "confidence": "EXTRACTED", "source_file": "D:\\AegisCore Intelligence Platform\\AegisCore Intelligence Platform\\frontend\\src\\lib\\api-compliance.ts", "source_location": "L42", "weight": 1.0}, {"source": "d_aegiscore_intelligence_platform_aegiscore_intelligence_platform_frontend_src_lib_api_compliance_ts", "target": "api_compliance_platformgetsecurityevents", "relation": "contains", "confidence": "EXTRACTED", "source_file": "D:\\AegisCore Intelligence Platform\\AegisCore Intelligence Platform\\frontend\\src\\lib\\api-compliance.ts", "source_location": "L57", "weight": 1.0}, {"source": "d_aegiscore_intelligence_platform_aegiscore_intelligence_platform_frontend_src_lib_api_compliance_ts", "target": "api_compliance_platformgetcomplianceframeworks", "relation": "contains", "confidence": "EXTRACTED", "source_file": "D:\\AegisCore Intelligence Platform\\AegisCore Intelligence Platform\\frontend\\src\\lib\\api-compliance.ts", "source_location": "L75", "weight": 1.0}, {"source": "d_aegiscore_intelligence_platform_aegiscore_intelligence_platform_frontend_src_lib_api_compliance_ts", "target": "api_compliance_platformrecalculatecompliance", "relation": "contains", "confidence": "EXTRACTED", "source_file": "D:\\AegisCore Intelligence Platform\\AegisCore Intelligence Platform\\frontend\\src\\lib\\api-compliance.ts", "source_location": "L90", "weight": 1.0}], "raw_calls": [{"caller_nid": "api_compliance_platformgetsecurityscore", "callee": "fetch", "source_file": "D:\\AegisCore Intelligence Platform\\AegisCore Intelligence Platform\\frontend\\src\\lib\\api-compliance.ts", "source_location": "L44"}, {"caller_nid": "api_compliance_platformgetsecurityscore", "callee": "apiUrl", "source_file": "D:\\AegisCore Intelligence Platform\\AegisCore Intelligence Platform\\frontend\\src\\lib\\api-compliance.ts", "source_location": "L44"}, {"caller_nid": "api_compliance_platformgetsecurityscore", "callee": "catch", "source_file": "D:\\AegisCore Intelligence Platform\\AegisCore Intelligence Platform\\frontend\\src\\lib\\api-compliance.ts", "source_location": "L50"}, {"caller_nid": "api_compliance_platformgetsecurityscore", "callee": "json", "source_file": "D:\\AegisCore Intelligence Platform\\AegisCore Intelligence Platform\\frontend\\src\\lib\\api-compliance.ts", "source_location": "L50"}, {"caller_nid": "api_compliance_platformgetsecurityscore", "callee": "json", "source_file": "D:\\AegisCore Intelligence Platform\\AegisCore Intelligence Platform\\frontend\\src\\lib\\api-compliance.ts", "source_location": "L54"}, {"caller_nid": "api_compliance_platformgetsecurityevents", "callee": "fetch", "source_file": "D:\\AegisCore Intelligence Platform\\AegisCore Intelligence Platform\\frontend\\src\\lib\\api-compliance.ts", "source_location": "L59"}, {"caller_nid": "api_compliance_platformgetsecurityevents", "callee": "apiUrl", "source_file": "D:\\AegisCore Intelligence Platform\\AegisCore Intelligence Platform\\frontend\\src\\lib\\api-compliance.ts", "source_location": "L60"}, {"caller_nid": "api_compliance_platformgetsecurityevents", "callee": "catch", "source_file": "D:\\AegisCore Intelligence Platform\\AegisCore Intelligence Platform\\frontend\\src\\lib\\api-compliance.ts", "source_location": "L68"}, {"caller_nid": "api_compliance_platformgetsecurityevents", "callee": "json", "source_file": "D:\\AegisCore Intelligence Platform\\AegisCore Intelligence Platform\\frontend\\src\\lib\\api-compliance.ts", "source_location": "L68"}, {"caller_nid": "api_compliance_platformgetsecurityevents", "callee": "json", "source_file": "D:\\AegisCore Intelligence Platform\\AegisCore Intelligence Platform\\frontend\\src\\lib\\api-compliance.ts", "source_location": "L72"}, {"caller_nid": "api_compliance_platformgetcomplianceframeworks", "callee": "fetch", "source_file": "D:\\AegisCore Intelligence Platform\\AegisCore Intelligence Platform\\frontend\\src\\lib\\api-compliance.ts", "source_location": "L77"}, {"caller_nid": "api_compliance_platformgetcomplianceframeworks", "callee": "apiUrl", "source_file": "D:\\AegisCore Intelligence Platform\\AegisCore Intelligence Platform\\frontend\\src\\lib\\api-compliance.ts", "source_location": "L77"}, {"caller_nid": "api_compliance_platformgetcomplianceframeworks", "callee": "catch", "source_file": "D:\\AegisCore Intelligence Platform\\AegisCore Intelligence Platform\\frontend\\src\\lib\\api-compliance.ts", "source_location": "L83"}, {"caller_nid": "api_compliance_platformgetcomplianceframeworks", "callee": "json", "source_file": "D:\\AegisCore Intelligence Platform\\AegisCore Intelligence Platform\\frontend\\src\\lib\\api-compliance.ts", "source_location": "L83"}, {"caller_nid": "api_compliance_platformgetcomplianceframeworks", "callee": "json", "source_file": "D:\\AegisCore Intelligence Platform\\AegisCore Intelligence Platform\\frontend\\src\\lib\\api-compliance.ts", "source_location": "L87"}, {"caller_nid": "api_compliance_platformrecalculatecompliance", "callee": "fetch", "source_file": "D:\\AegisCore Intelligence Platform\\AegisCore Intelligence Platform\\frontend\\src\\lib\\api-compliance.ts", "source_location": "L97"}, {"caller_nid": "api_compliance_platformrecalculatecompliance", "callee": "apiUrl", "source_file": "D:\\AegisCore Intelligence Platform\\AegisCore Intelligence Platform\\frontend\\src\\lib\\api-compliance.ts", "source_location": "L97"}, {"caller_nid": "api_compliance_platformrecalculatecompliance", "callee": "catch", "source_file": "D:\\AegisCore Intelligence Platform\\AegisCore Intelligence Platform\\frontend\\src\\lib\\api-compliance.ts", "source_location": "L103"}, {"caller_nid": "api_compliance_platformrecalculatecompliance", "callee": "json", "source_file": "D:\\AegisCore Intelligence Platform\\AegisCore Intelligence Platform\\frontend\\src\\lib\\api-compliance.ts", "source_location": "L103"}, {"caller_nid": "api_compliance_platformrecalculatecompliance", "callee": "json", "source_file": "D:\\AegisCore Intelligence Platform\\AegisCore Intelligence Platform\\frontend\\src\\lib\\api-compliance.ts", "source_location": "L107"}]}